ret_tools/__init__.py
ret_tools/ret_tools.py
ret_tools-1.0.4.dist-info/METADATA
ret_tools-1.0.4.dist-info/WHEEL
ret_tools-1.0.4.dist-info/top_level.txt
ret_tools-1.0.4.dist-info/RECORD
