Metadata-Version: 2.1
Name: ret-tools
Version: 1.0.4
Summary: Easy-to-use tools for handling function responses, handling exceptions, and creating asynchronous tasks.
Home-page: https://github.com/rileydylan581/ret-tools
Author: "Dylan Riley"
Author-email: rileydylan581@gmail.com
License: UNKNOWN
Platform: UNKNOWN
Classifier: Programming Language :: Python :: 3
Classifier: Operating System :: OS Independent
Requires-Python: >=3.6
